pysmaev/__init__.py
pysmaev/const.py
pysmaev/core.py
pysmaev/exceptions.py
pysmaev/helpers.py
pysmaev-0.1.7.dist-info/LICENSE
pysmaev-0.1.7.dist-info/METADATA
pysmaev-0.1.7.dist-info/WHEEL
pysmaev-0.1.7.dist-info/top_level.txt
pysmaev-0.1.7.dist-info/RECORD
